odoo/addons/l10n_nl_tax_statement/README.rst
odoo/addons/l10n_nl_tax_statement/__init__.py
odoo/addons/l10n_nl_tax_statement/__manifest__.py
odoo/addons/l10n_nl_tax_statement/data/paperformat.xml
odoo/addons/l10n_nl_tax_statement/i18n/nl.po
odoo/addons/l10n_nl_tax_statement/i18n/nl_NL.po
odoo/addons/l10n_nl_tax_statement/models/__init__.py
odoo/addons/l10n_nl_tax_statement/models/l10n_nl_vat_statement.py
odoo/addons/l10n_nl_tax_statement/models/l10n_nl_vat_statement_config.py
odoo/addons/l10n_nl_tax_statement/models/l10n_nl_vat_statement_line.py
odoo/addons/l10n_nl_tax_statement/report/report_tax_statement.xml
odoo/addons/l10n_nl_tax_statement/security/ir.model.access.csv
odoo/addons/l10n_nl_tax_statement/security/tax_statement_security_rule.xml
odoo/addons/l10n_nl_tax_statement/static/src/css/report.css
odoo/addons/l10n_nl_tax_statement/templates/assets.xml
odoo/addons/l10n_nl_tax_statement/tests/__init__.py
odoo/addons/l10n_nl_tax_statement/tests/test_l10n_nl_vat_statement.py
odoo/addons/l10n_nl_tax_statement/views/l10n_nl_vat_statement_view.xml
odoo/addons/l10n_nl_tax_statement/views/report_tax_statement.xml
odoo/addons/l10n_nl_tax_statement/wizard/__init__.py
odoo/addons/l10n_nl_tax_statement/wizard/l10n_nl_vat_statement_config_wizard.py
odoo/addons/l10n_nl_tax_statement/wizard/l10n_nl_vat_statement_config_wizard.xml
odoo11_addon_l10n_nl_tax_statement-11.0.1.1.0.dist-info/DESCRIPTION.rst
odoo11_addon_l10n_nl_tax_statement-11.0.1.1.0.dist-info/METADATA
odoo11_addon_l10n_nl_tax_statement-11.0.1.1.0.dist-info/RECORD
odoo11_addon_l10n_nl_tax_statement-11.0.1.1.0.dist-info/WHEEL
odoo11_addon_l10n_nl_tax_statement-11.0.1.1.0.dist-info/metadata.json
odoo11_addon_l10n_nl_tax_statement-11.0.1.1.0.dist-info/top_level.txt
